subforge/__init__.py
subforge/__main__.py
subforge/cli.py
subforge/generators.py
subforge/simple_cli.py
subforge/core/__init__.py
subforge/core/cache_manager.py
subforge/core/communication.py
subforge/core/context_engineer.py
subforge/core/mcp_task_manager.py
subforge/core/project_analyzer.py
subforge/core/prp_generator.py
subforge/core/validation_engine.py
subforge/core/workflow_orchestrator.py
subforge/core/testing/__init__.py
subforge/core/testing/test_generator.py
subforge/core/testing/test_runner.py
subforge/core/testing/test_validator.py
subforge/templates/__init__.py
subforge/templates/api-developer.md
subforge/templates/backend-developer.md
subforge/templates/code-reviewer.md
subforge/templates/data-scientist.md
subforge/templates/database-specialist.md
subforge/templates/devops-engineer.md
subforge/templates/documentation-specialist.md
subforge/templates/frontend-developer.md
subforge/templates/intelligent_templates.py
subforge/templates/orchestrator.md
subforge/templates/performance-optimizer.md
subforge/templates/security-auditor.md
subforge/templates/test-engineer.md
subforge/templates/factory/agent-generator.md
subforge/templates/factory/claude-md-generator.md
subforge/templates/factory/deployment-validator.md
subforge/templates/factory/project-analyzer.md
subforge/templates/factory/template-selector.md
subforge/templates/factory/workflow-generator.md
subforge/templates/use-cases/data-analytics-pipeline.md
subforge/templates/use-cases/enterprise-integration.md
subforge/templates/use-cases/machine-learning-ops.md
subforge/templates/use-cases/microservices-api.md
subforge/templates/use-cases/web-app-fullstack.md
subforge-1.1.0.dist-info/licenses/LICENSE
subforge-1.1.0.dist-info/METADATA
subforge-1.1.0.dist-info/WHEEL
subforge-1.1.0.dist-info/entry_points.txt
subforge-1.1.0.dist-info/top_level.txt
subforge-1.1.0.dist-info/RECORD
