Metadata-Version: 2.4
Name: subforge
Version: 1.1.0
Summary: AI-powered subagent factory for Claude Code developers
Home-page: https://github.com/FAL1989/subforge
Author: SubForge Contributors
Author-email: 
License: MIT License
Project-URL: Homepage, https://github.com/FAL1989/subforge
Project-URL: Documentation, https://github.com/FAL1989/subforge#readme
Project-URL: Repository, https://github.com/FAL1989/subforge
Project-URL: Issues, https://github.com/FAL1989/subforge/issues
Keywords: claude,ai,subagents,automation,development,tools,cli,orchestration
Classifier: Development Status :: 3 - Alpha
Classifier: Intended Audience :: Developers
Classifier: Topic :: Software Development :: Code Generators
Classifier: Topic :: Software Development :: Build Tools
Classifier: Topic :: Software Development :: Libraries :: Python Modules
Classifier: License :: OSI Approved :: MIT License
Classifier: Programming Language :: Python :: 3
Classifier: Programming Language :: Python :: 3.8
Classifier: Programming Language :: Python :: 3.9
Classifier: Programming Language :: Python :: 3.10
Classifier: Programming Language :: Python :: 3.11
Classifier: Programming Language :: Python :: 3.12
Classifier: Operating System :: OS Independent
Classifier: Environment :: Console
Classifier: Framework :: AsyncIO
Requires-Python: >=3.8
License-File: LICENSE
Provides-Extra: rich
Requires-Dist: typer>=0.9.0; extra == "rich"
Requires-Dist: rich>=13.0.0; extra == "rich"
Provides-Extra: dev
Requires-Dist: flake8>=6.0.0; extra == "dev"
Requires-Dist: black>=23.0.0; extra == "dev"
Requires-Dist: autopep8>=2.0.0; extra == "dev"
Requires-Dist: ruff>=0.1.0; extra == "dev"
Requires-Dist: pytest>=7.0.0; extra == "dev"
Requires-Dist: pytest-asyncio>=0.21.0; extra == "dev"
Requires-Dist: pytest-cov>=4.0.0; extra == "dev"
Provides-Extra: full
Requires-Dist: typer>=0.9.0; extra == "full"
Requires-Dist: rich>=13.0.0; extra == "full"
Requires-Dist: flake8>=6.0.0; extra == "full"
Requires-Dist: black>=23.0.0; extra == "full"
Requires-Dist: autopep8>=2.0.0; extra == "full"
Requires-Dist: ruff>=0.1.0; extra == "full"
Dynamic: home-page
Dynamic: license-file
Dynamic: requires-python
